vitriini/__init__.py
vitriini/__main__.py
vitriini/api.py
vitriini/cli.py
vitriini/processor.py
vitriini/showcase.py
vitriini-2023.10.22.dist-info/LICENSE
vitriini-2023.10.22.dist-info/METADATA
vitriini-2023.10.22.dist-info/WHEEL
vitriini-2023.10.22.dist-info/entry_points.txt
vitriini-2023.10.22.dist-info/top_level.txt
vitriini-2023.10.22.dist-info/RECORD
